{
    "extEnable": true,
    "extAppid": "wxc5efcf7fed223f27",
    "directCommit": false,
    "ext": {
        "name": "wechat",
        "_appids": [
            "wx88930b745db66d86-体验官测试(DEV专用)",
            "wx2965f7b7841f6f51-链卡AI(DEV测试)",
            "wx7246cb6517a8c773-名片演示(正式专用)",
            "wxa726069f668cf10b-链卡科技(正式专用)",
            "wx7242221200872d80-群友名片(个人版专用)",
            "wx0a3ed3d4750630ba-汇桔宝(汇桔宝专用)",
            "wxbf8ec6ea45074ddc-链卡商圈(商圈专用)",
            "wx910cc0280415c976-小T博士(TCL专用)",
            "wxc5efcf7fed223f27-体验官讲师端",
            "wx959eb73a36146301-车讯达",
            "wx7ca64061229ce8b2-风神",
            "wx231168e9e1ccdc88-广汽传祺智慧4S店",
            "wxe6ffa5dceb3b003b-长安汽车促销",
            "wxdd08a443a79d0101-东风日产智慧专营店",
            "wxe1fdbef0df51a3b8-4S名片"
        ],
        "extAppName": "企业名称EXT",
        "extAppLogo": "http://wx.qlogo.cn/mmopen/dx5fDNn1icfaqOiaVCylRRJtGyANawjjoSLWvXnwO8PGEL21FdCcBGHvaMNjlmpwPe4TdBE84Kor5icAMRdUfodgia7ky0tM9t9G/0",
        "extAppid": "wx231168e9e1ccdc88",
        "baseUrl": "https://cxd.m0.hk",
        "socketUrl": "https://cxd.m0.hk",
        "isCorporation": true,
        "isCircle": false,
        "nearlyAllot": true,
        "isTcl": true,
        "isCxd": 1,
        "branchName": "链卡",
        "routeSaleHomeByFirst": true
    },
    "permission": {
        "scope.userLocation": {
            "desc": "正在获取你的位置信息，为你找到最近的门店"
        }
    }
}