{
    "component": true,
    "usingComponents": {
        "brands": "./modules/brands/index",
        "carousel": "./modules/carousel/index",
        "coupon": "./modules/coupon/index",
        "img-advert": "./modules/img_advert/index",
        "img-nav": "./modules/img_nav/index",
        "miaosha": "./modules/miaosha/index",
        "nearstore": "./modules/nearstore/index",
        "newsinfo": "./modules/newsinfo/index",
        "products": "./modules/products/index",
        "services": "./modules/services/index",
        "supplyinfo": "./modules/supplyinfo/index",
        "title": "./modules/title/index",
        "tuan": "./modules/tuan/index",
        "cvideo": "./modules/video/index",
        "giftcard": "./modules/giftcard/index",
        "vipcard": "./modules/vipcard/index",
        "c-form": "./modules/form/form",
        "comment": "./modules/comment/index",
        "img-advert-fx": "./modules/img_advert_fx/index",
        "hotel": "./modules/hotel/index",
        "text-nav": "./modules/text_nav/index",
        "img-text": "./modules/img_text/index",
        "notice": "./modules/notice/index",
        "groups": "./modules/groups/index",
        "hotels": "./modules/hotellist/index"
    }
}